rdtwt/__init__.py
rdtwt/apps.py
rdtwt/runner.py
django_rdtwt-3.0.0.dist-info/LICENSE
django_rdtwt-3.0.0.dist-info/METADATA
django_rdtwt-3.0.0.dist-info/WHEEL
django_rdtwt-3.0.0.dist-info/top_level.txt
django_rdtwt-3.0.0.dist-info/RECORD
