Metadata-Version: 2.1
Name: django-rdtwt
Version: 3.0.0
Summary: Run Django tests with testcontainers.
Home-page: https://github.com/wonkybream/django-rdtwt
Author: Sampo Lavinen
License: MIT
Keywords: django,testing,testcontainers,docker,test automation
Classifier: Intended Audience :: Developers
Classifier: Development Status :: 4 - Beta
Classifier: License :: OSI Approved :: MIT License
Classifier: Framework :: Django
Classifier: Framework :: Django :: 4.2
Classifier: Framework :: Django :: 5.0
Classifier: Framework :: Django :: 5.1
Classifier: Programming Language :: Python
Classifier: Programming Language :: Python :: 3.10
Classifier: Programming Language :: Python :: 3.11
Classifier: Programming Language :: Python :: 3.12
Classifier: Programming Language :: Python :: 3.13
Classifier: Operating System :: OS Independent
Requires-Python: >=3.10
License-File: LICENSE
Requires-Dist: testcontainers
Requires-Dist: Django
Requires-Dist: psycopg
